fluidai_mcp/__init__.py
fluidai_mcp/cli.py
fluidai_mcp/services/__init__.py
fluidai_mcp/services/env_manager.py
fluidai_mcp/services/network_utils.py
fluidai_mcp/services/package_installer.py
fluidai_mcp/services/package_launcher.py
fluidai_mcp/services/package_list.py
fluidai_mcp/services/s3_utils.py
fluidmcp-0.1.0.dist-info/licenses/LICENSE
fluidmcp-0.1.0.dist-info/METADATA
fluidmcp-0.1.0.dist-info/WHEEL
fluidmcp-0.1.0.dist-info/entry_points.txt
fluidmcp-0.1.0.dist-info/top_level.txt
fluidmcp-0.1.0.dist-info/RECORD
