Metadata-Version: 2.4
Name: fluidmcp
Version: 0.1.0
Summary: A CLI tool for installing and managing Model Context Protocol (MCP) servers
Home-page: https://github.com/Fluid-AI/fluidmcp
Author: Fluid AI
Author-email: info@fluid.ai
Keywords: mcp,model context protocol,llm,ai,fluidai
Classifier: Programming Language :: Python :: 3
Classifier: License :: OSI Approved :: GNU General Public License v3 (GPLv3)
Classifier: Operating System :: OS Independent
Classifier: Development Status :: 4 - Beta
Classifier: Intended Audience :: Developers
Classifier: Topic :: Software Development :: Libraries :: Python Modules
Requires-Python: >=3.6
License-File: LICENSE
Requires-Dist: requests
Requires-Dist: loguru
Requires-Dist: pathlib
Requires-Dist: psutil
Requires-Dist: boto3
Dynamic: author
Dynamic: author-email
Dynamic: classifier
Dynamic: description
Dynamic: description-content-type
Dynamic: home-page
Dynamic: keywords
Dynamic: license-file
Dynamic: requires-dist
Dynamic: requires-python
Dynamic: summary
